weathermentations/__init__.py
weathermentations/exposure.py
weathermentations/rain.py
weathermentations/raindrop/__init__.py
weathermentations/raindrop/config.py
weathermentations/raindrop/dropgenerator.py
weathermentations/raindrop/raindrop.py
weathermentations-0.3.0.dist-info/METADATA
weathermentations-0.3.0.dist-info/WHEEL
weathermentations-0.3.0.dist-info/top_level.txt
weathermentations-0.3.0.dist-info/RECORD
